adk/__init__.py
adk/rpc/__init__.py
adk/rpc/rpc_cfg.py
adk/rpc/rpc_manager.py
adk/rpc/rpc_service.py
adk/utils/__init__.py
adk/utils/aio_tools.py
adk/utils/cron_executor.py
adk/utils/priority_datatypes.py
adk/utils/taskque.py
adk-0.0.5.dist-info/LICENSE
adk-0.0.5.dist-info/METADATA
adk-0.0.5.dist-info/WHEEL
adk-0.0.5.dist-info/entry_points.txt
adk-0.0.5.dist-info/top_level.txt
adk-0.0.5.dist-info/RECORD
