Metadata-Version: 2.1
Name: adk
Version: 0.0.5
Summary: A ADK-dev Kit
Home-page: https://github.com/qsrc/ADK
Author: Attoy
Author-email: attoy@hotmail.com
License: UNKNOWN
Platform: UNKNOWN
Classifier: Programming Language :: Python :: 3
Classifier: License :: OSI Approved :: MIT License
Classifier: Operating System :: OS Independent
Requires-Python: >=3.7
